pypika-stubs/__init__.pyi
pypika-stubs/analytics.pyi
pypika-stubs/dialects.pyi
pypika-stubs/enums.pyi
pypika-stubs/functions.pyi
pypika-stubs/pseudocolumns.pyi
pypika-stubs/py.typed
pypika-stubs/queries.pyi
pypika-stubs/terms.pyi
pypika-stubs/utils.pyi
pypika-stubs/clickhouse/__init__.pyi
pypika-stubs/clickhouse/array.pyi
pypika-stubs/clickhouse/condition.pyi
pypika-stubs/clickhouse/dates_and_times.pyi
pypika-stubs/clickhouse/nullable_arg.pyi
pypika-stubs/clickhouse/search_string.pyi
pypika-stubs/clickhouse/type_conversion.pyi
pypika_stubs-0.48.0a1.dist-info/METADATA
pypika_stubs-0.48.0a1.dist-info/WHEEL
pypika_stubs-0.48.0a1.dist-info/top_level.txt
pypika_stubs-0.48.0a1.dist-info/RECORD
