Metadata-Version: 2.1
Name: pypika-stubs
Version: 0.48.0a1
Summary: pypika typing stubs
Author-email: trim21 <trim21me@gmail.com>
License: MIT
Project-URL: Homepage, https://github.com/trim21/pypika-stubs
Classifier: Development Status :: 4 - Beta
Classifier: Intended Audience :: Developers
Classifier: Typing :: Typed
Requires-Python: ~=3.8
Requires-Dist: pypika <0.49.0,>=0.48.9
Provides-Extra: dev
Requires-Dist: pre-commit ==3.8.0 ; (python_version >= "3.9") and extra == 'dev'
Requires-Dist: mypy ==1.11.1 ; (python_version >= "3.9") and extra == 'dev'
